pyflirt/__init__.py
pyflirt/api.py
pyflirt/data.py
pyflirt-0.1.0.dist-info/licenses/LICENSE
pyflirt-0.1.0.dist-info/METADATA
pyflirt-0.1.0.dist-info/WHEEL
pyflirt-0.1.0.dist-info/top_level.txt
pyflirt-0.1.0.dist-info/RECORD
