Metadata-Version: 2.4
Name: pyflirt
Version: 0.1.0
Summary: A lighthearted Python package for developer-themed pickup lines.
Author-email: Daniel <dl4458@nyu.edu>
License:                     GNU GENERAL PUBLIC LICENSE
Project-URL: Homepage, https://github.com/swe-students-fall2025/3-python-package-team_quartz
Project-URL: Repository, https://github.com/swe-students-fall2025/3-python-package-team_quartz.git
Project-URL: Bug Tracker, https://github.com/swe-students-fall2025/3-python-package-team_quartz/issues
Keywords: fun,pickup lines,developer humor
Classifier: Programming Language :: Python :: 3
Classifier: Intended Audience :: Developers
Classifier: License :: OSI Approved :: MIT License
Classifier: Operating System :: OS Independent
Requires-Python: >=3.9
License-File: LICENSE
Provides-Extra: dev
Requires-Dist: pytest; extra == "dev"
Dynamic: license-file
